ioteq/__init__.py
ioteq/cloud/__init__.py
ioteq/cloud/iot_v1/__init__.py
ioteq/cloud/iot_v1/client.py
ioteq/cloud/iot_v1/config.py
ioteq/cloud/iot_v1/config_manager.py
ioteq/cloud/iot_v1/developer_tests.py
ioteq/cloud/iot_v1/device_types.py
ioteq/cloud/iot_v1/devices.py
ioteq/cloud/iot_v1/http_client.py
ioteq/cloud/iot_v1/pagers.py
ioteq/cloud/iot_v1/registry.py
ioteq/cloud/iot_v1/registry_types.py
ioteq/cloud/iot_v1/resources.py
ioteq/cloud/iot_v1/utils.py
ioteq_cloud_iot-1.0.8.dist-info/LICENSE
ioteq_cloud_iot-1.0.8.dist-info/METADATA
ioteq_cloud_iot-1.0.8.dist-info/WHEEL
ioteq_cloud_iot-1.0.8.dist-info/top_level.txt
ioteq_cloud_iot-1.0.8.dist-info/RECORD
