Metadata-Version: 2.1
Name: ioteq-cloud-iot
Version: 1.0.8
Summary: Cloud IoT API client library
Home-page: https://github.com/aeoberto/python-iot
Author: Angel Oberto
Author-email: angel.oberto@io-teq.com
License: Apache 2.0
Project-URL: Bug Reports, https://github.com/aeoberto/python-iot/issues
Project-URL: Source, https://github.com/aeoberto/python-iot
Project-URL: Documentation, https://github.com/aeoberto/python-iot#readme
Platform: Posix; MacOS X; Windows
Classifier: Development Status :: 5 - Production/Stable
Classifier: Intended Audience :: Developers
Classifier: License :: OSI Approved :: Apache Software License
Classifier: Programming Language :: Python
Classifier: Programming Language :: Python :: 3
Classifier: Programming Language :: Python :: 3.8
Classifier: Programming Language :: Python :: 3.9
Classifier: Programming Language :: Python :: 3.10
Classifier: Programming Language :: Python :: 3.11
Classifier: Operating System :: OS Independent
Classifier: Topic :: Internet
Requires-Python: >=3.8
Requires-Dist: httpx
Requires-Dist: proto-plus
